LICENSE
README.md
serializer_inference/__init__.py
serializer_inference/inference.py
serializer_inference/py.typed
serializer_inference/serializers.py
serializer_inference/typing.py
serializer_inference/utils.py
drf_serializer_inference-0.0.2.dist-info/LICENSE
drf_serializer_inference-0.0.2.dist-info/METADATA
drf_serializer_inference-0.0.2.dist-info/WHEEL
drf_serializer_inference-0.0.2.dist-info/RECORD
