Metadata-Version: 2.1
Name: drf-serializer-inference
Version: 0.0.2
Summary: Infer Django Rest Framework serializers from callables like functions and classes.
Home-page: https://mrthearman.github.io/drf-serializer-inference
License: MIT
Keywords: drf,django,rest_framework,rest,framework,inference,serializer
Author: Matti Lamppu
Author-email: lamppu.matti.akseli@gmail.com
Requires-Python: >=3.9,<4
Classifier: Environment :: Web Environment
Classifier: Intended Audience :: Developers
Classifier: License :: OSI Approved :: MIT License
Classifier: Natural Language :: English
Classifier: Operating System :: OS Independent
Classifier: Programming Language :: Python
Classifier: Programming Language :: Python :: 3
Classifier: Programming Language :: Python :: 3.9
Classifier: Programming Language :: Python :: 3.10
Classifier: Programming Language :: Python :: 3.11
Classifier: Programming Language :: Python :: 3
Classifier: Programming Language :: Python :: 3 :: Only
Classifier: Programming Language :: Python :: 3.10
Classifier: Programming Language :: Python :: 3.11
Classifier: Programming Language :: Python :: 3.9
Provides-Extra: pydantic
Requires-Dist: djangorestframework (>=3.12.0)
Requires-Dist: pydantic (>=1.6.2) ; extra == "pydantic"
Requires-Dist: typing-extensions (>=4.4.0) ; python_version < "3.10"
Project-URL: Bug Tracker, https://github.com/MrThearMan/drf-serializer-inference/issues
Project-URL: Repository, https://github.com/MrThearMan/drf-serializer-inference
